Metadata-Version: 2.1
Name: fryptos
Version: 0.0.8
Summary: Encrypt files.
Home-page: https://github.com/pyohei/Fryptos
Author: Shohei Mukai
Author-email: mukaishohei76@gmail.com
License: MIT
Keywords: encrypt file
Platform: UNKNOWN
Classifier: Programming Language :: Python
